LICENSE
MANIFEST.in
README.md
setup.cfg
setup.py
django_param_field.egg-info/PKG-INFO
django_param_field.egg-info/SOURCES.txt
django_param_field.egg-info/dependency_links.txt
django_param_field.egg-info/not-zip-safe
django_param_field.egg-info/requires.txt
django_param_field.egg-info/top_level.txt
param_field/__init__.py
param_field/apps.py
param_field/conf.py
param_field/forms.py
param_field/models.py
param_field/params.py
param_field/parser.py
param_field/validators.py
param_field/tests/__init__.py
param_field/tests/test_conf.py
param_field/tests/test_fields.py
param_field/tests/test_forms.py
param_field/tests/test_models.py
param_field/tests/test_params.py
param_field/tests/test_parser.py
param_field/tests/test_validators.py