Metadata-Version: 1.1
Name: django-param-field
Version: 0.4.0
Summary: A Django model field that uses a DSL to define, generate, and validate, custom forms
Home-page: https://github.com/secnot/django-param-field
Author: secnot
Author-email: UNKNOWN
License: LPGL, see LICENSE file.
Keywords: django,dsl,model,field,pyparsing
Platform: UNKNOWN
Classifier: Topic :: Utilities
Classifier: Natural Language :: English
Classifier: Operating System :: OS Independent
Classifier: Intended Audience :: Developers
Classifier: License :: OSI Approved :: GNU Lesser General Public License v3 (LGPLv3)
Classifier: Development Status :: 4 - Beta
Classifier: Environment :: Web Environment
Classifier: Framework :: Django
Classifier: Framework :: Django :: 1.9
Classifier: Programming Language :: Python
Classifier: Programming Language :: Python :: 3
Classifier: Topic :: Internet :: WWW/HTTP
